{
  "main": {
    "id": "5391111ce72ef8e9",
    "type": "split",
    "children": [
      {
        "id": "4864f7504a10e7e2",
        "type": "tabs",
        "children": [
          {
            "id": "f800c653273e40cc",
            "type": "leaf",
            "state": {
              "type": "markdown",
              "state": {
                "file": "大學課程/大二下/微處理機/Final_Project/第一部分.md",
                "mode": "source",
                "source": false
              },
              "icon": "lucide-file",
              "title": "第一部分"
            }
          },
          {
            "id": "4f9e27b5e1ec5c4f",
            "type": "leaf",
            "state": {
              "type": "markdown",
              "state": {
                "file": "大學課程/大二下/微處理機/Final_Project/第二部分.md",
                "mode": "source",
                "source": false
              },
              "icon": "lucide-file",
              "title": "第二部分"
            }
          },
          {
            "id": "351e8addbeb4b135",
            "type": "leaf",
            "state": {
              "type": "markdown",
              "state": {
                "file": "大學課程/大二下/微處理機/Final_Project/第三部分.md",
                "mode": "source",
                "source": false
              },
              "icon": "lucide-file",
              "title": "第三部分"
            }
          },
          {
            "id": "0ab8ce7327b035de",
            "type": "leaf",
            "state": {
              "type": "markdown",
              "state": {
                "file": "大學課程/大二下/微處理機/Final_Project/第四部份.md",
                "mode": "source",
                "source": false
              },
              "icon": "lucide-file",
              "title": "第四部份"
            }
          }
        ],
        "currentTab": 2
      }
    ],
    "direction": "vertical"
  },
  "left": {
    "id": "e4f1020c61d9367d",
    "type": "split",
    "children": [
      {
        "id": "f7621600ea2d22bd",
        "type": "tabs",
        "children": [
          {
            "id": "2db8f61ee86329d3",
            "type": "leaf",
            "state": {
              "type": "file-explorer",
              "state": {
                "sortOrder": "alphabetical",
                "autoReveal": false
              },
              "icon": "lucide-folder-closed",
              "title": "檔案瀏覽器"
            }
          },
          {
            "id": "1b9bc19af6cd6315",
            "type": "leaf",
            "state": {
              "type": "search",
              "state": {
                "query": "",
                "matchingCase": false,
                "explainSearch": false,
                "collapseAll": false,
                "extraContext": false,
                "sortOrder": "alphabetical"
              },
              "icon": "lucide-search",
              "title": "搜尋"
            }
          },
          {
            "id": "3851ce67e2dc10fa",
            "type": "leaf",
            "state": {
              "type": "bookmarks",
              "state": {},
              "icon": "lucide-bookmark",
              "title": "書籤"
            }
          },
          {
            "id": "771027632233698e",
            "type": "leaf",
            "state": {
              "type": "mk-path-view",
              "state": {},
              "icon": "layout-grid",
              "title": "Navigator"
            }
          }
        ],
        "currentTab": 3
      }
    ],
    "direction": "horizontal",
    "width": 425.51625061035156
  },
  "right": {
    "id": "9faf2416e2c6517e",
    "type": "split",
    "children": [
      {
        "id": "f1fc07d4517801fb",
        "type": "tabs",
        "children": [
          {
            "id": "5e6f2e3ad68b226f",
            "type": "leaf",
            "state": {
              "type": "backlink",
              "state": {
                "file": "日記/2024-11-10.md",
                "collapseAll": false,
                "extraContext": false,
                "sortOrder": "alphabetical",
                "showSearch": false,
                "searchQuery": "",
                "backlinkCollapsed": false,
                "unlinkedCollapsed": true
              },
              "icon": "links-coming-in",
              "title": "2024-11-10 的反向連結"
            }
          },
          {
            "id": "c9698e1b97063c6a",
            "type": "leaf",
            "state": {
              "type": "outgoing-link",
              "state": {
                "file": "未命名.md",
                "linksCollapsed": false,
                "unlinkedCollapsed": true
              },
              "icon": "links-going-out",
              "title": "未命名 的對外連結"
            }
          },
          {
            "id": "4f3dbf0e3a308b18",
            "type": "leaf",
            "state": {
              "type": "tag",
              "state": {
                "sortOrder": "frequency",
                "useHierarchy": true,
                "showSearch": false,
                "searchQuery": ""
              },
              "icon": "lucide-tags",
              "title": "標籤"
            }
          },
          {
            "id": "e25fdfe018c975eb",
            "type": "leaf",
            "state": {
              "type": "outline",
              "state": {
                "file": "大學課程/大二下/微處理機/Final_Project/第一部分.md",
                "followCursor": false,
                "showSearch": false,
                "searchQuery": ""
              },
              "icon": "lucide-list",
              "title": "第一部分 的大綱"
            }
          },
          {
            "id": "1bd00b3b415ff145",
            "type": "leaf",
            "state": {
              "type": "side-panel-control-view",
              "state": {},
              "icon": "viewIcon",
              "title": "Markdown-Autocomplete"
            }
          },
          {
            "id": "a8c1871124e4e79e",
            "type": "leaf",
            "state": {
              "type": "calendar",
              "state": {},
              "icon": "calendar-with-checkmark",
              "title": "Calendar"
            }
          },
          {
            "id": "baa44dea0c84c8f8",
            "type": "leaf",
            "state": {
              "type": "quiet-outline",
              "state": {},
              "icon": "lines-of-text",
              "title": "Quiet Outline"
            }
          },
          {
            "id": "19116af9bae892e7",
            "type": "leaf",
            "state": {
              "type": "git-view",
              "state": {},
              "icon": "git-pull-request",
              "title": "Source Control"
            }
          }
        ],
        "currentTab": 7
      }
    ],
    "direction": "horizontal",
    "width": 349.5
  },
  "left-ribbon": {
    "hiddenItems": {
      "markdown-importer:開啟 Markdown 格式轉換器": false,
      "switcher:開啟快速切換": false,
      "graph:查看關聯圖": false,
      "canvas:建立新畫布": false,
      "daily-notes:開啟今天的每日筆記": false,
      "templates:插入模板": false,
      "command-palette:開啟命令面板": false,
      "obsidian-markdown-formatting-assistant-plugin:Open Markdown Formatting Assistant": false,
      "templater-obsidian:Templater": false,
      "pdf-plus:PDF++: Toggle auto-copy": false,
      "pdf-plus:PDF++: Toggle auto-focus": false,
      "pdf-plus:PDF++: Toggle auto-paste": false,
      "media-extended:Open media": false,
      "obsidian-git:Open Git source control": false,
      "obsidian-excalidraw-plugin:New drawing": false,
      "table-editor-obsidian:Advanced Tables Toolbar": false,
      "obsidian-importer:Open Importer": false,
      "vscode-editor:新建程式碼檔案": false,
      "obsidian-kanban:Create new board": false
    }
  },
  "active": "351e8addbeb4b135",
  "lastOpenFiles": [
    "大學課程/大二下/微處理機/Final_Project/第四部份.md",
    "大學課程/大二下/微處理機/Final_Project/Final_Project.md",
    "大學課程/大二下/微處理機/Final_Project/第三部分.md",
    "大學課程/大二下/微處理機/Final_Project/第三部分/第三部分-1749459260216.png",
    "大學課程/大二下/微處理機/Final_Project/第一部分.md",
    "大學課程/大二下/微處理機/Final_Project/第二部分.md",
    "大學課程/大二下/微處理機/Final_Project/第三部分/第三部分-1749457794373.png",
    "大學課程/大二下/微處理機/Final_Project/第三部分",
    "大學課程/大二下/微處理機/Final_Project/第二部分/第二部分-1749456558678.png",
    "大學課程/大二下/微處理機/Final_Project/第二部分/第二部分-1749455563142.png",
    "大學課程/大二下/微處理機/Final_Project/第二部分",
    "大學課程/大二下/微處理機/課程筆記/第六章/第六章.md",
    "大學課程/大二下/微處理機/Final_Project/第一部分/第一部分-1749139684418.png",
    "大學課程/大二下/微處理機/課程筆記/第四章/第四章.md",
    "大學課程/大二下/微處理機/Final_Project/第一部分/第一部分-1749137367875.png",
    "大學課程/大二下/微處理機/Final_Project/第一部分/第一部分-1749137288915.png",
    "大學課程/大二下/微處理機/課堂作業/lab_14.md",
    "大學課程/大二下/微處理機/Final_Project/第一部分/第一部分-1749136290635.png",
    "大學課程/大二下/微處理機/課堂作業/課堂作業.md",
    "大學課程/大二下/演算法/期末考筆記/演算法筆記_Lec08_堆積排序.md",
    "大學課程/大二下/微處理機/課程筆記/微處理機概述.md",
    "大學課程/大二下/微處理機/Final_Project/第一部分",
    "大學課程/大二下/微處理機/Final_Project",
    "大學課程/大二下/微處理機/Untitled.md",
    "大學課程/大二下/Unix系統與Script程式設計/期末考筆記/考古/Final_GroupB_2024_Sol.pdf",
    "大學課程/大二下/演算法/期末考筆記/演算法筆記_Lec11_最短路徑.md",
    "大學課程/大二下/演算法/期末考筆記/演算法筆記_Lec10_最小生成樹.md",
    "大學課程/大二下/演算法/期末考筆記/演算法筆記_Lec07_計數排序.md",
    "大學課程/大二下/演算法/期末考筆記/演算法筆記_Lec05_大師定理.md",
    "大學課程/大二下/Unix系統與Script程式設計/期末考筆記/考古/Final_GroupB_2024.pdf",
    "大學課程/大二下/Unix系統與Script程式設計/期末考筆記/考古/114-Final-2.jpg",
    "大學課程/大二下/Unix系統與Script程式設計/期末考筆記/考古/114-Final-1.jpg",
    "大學課程/大二下/Unix系統與Script程式設計/期末考筆記/考古/113-Final.pdf",
    "大學課程/大二下/Unix系統與Script程式設計/期末考筆記/考古/Final_2023_sol.pdf",
    "大學課程/大二下/Unix系統與Script程式設計/期末考筆記/行程.md",
    "大學課程/大二下/Unix系統與Script程式設計/期末考筆記/考古/Final_GroupA_2024.pdf",
    "大學課程/大二下/Unix系統與Script程式設計/期末考筆記/考古/Final_2024.pdf",
    "大學課程/大二下/Unix系統與Script程式設計/期末考筆記/檔案分享.md",
    "大學課程/大二下/Unix系統與Script程式設計/期末考筆記/Unix學習筆記_總覽.md",
    "大學課程/大二下/Unix系統與Script程式設計/期末考筆記/Shell程式設計.md",
    "大學課程/大二下/Unix系統與Script程式設計/期末考筆記/基本檔案處理.md",
    "大學課程/大二下/Unix系統與Script程式設計/期末考筆記/考古/考古.md",
    "大學課程/大二下/Unix系統與Script程式設計/期末考筆記/期末考筆記.md",
    "大學課程/大二下/Unix系統與Script程式設計/期末考筆記/homework/homework.md",
    "大學課程/大二下/演算法/期末考筆記/演算法筆記_Lec09_圖形搜尋與拓樸排序.md",
    "大學課程/大二下/Unix系統與Script程式設計/期末考筆記/進階檔案處理.md",
    "未命名.canvas",
    "ue5_GSproject/未命名.canvas",
    "未命名 1.canvas"
  ]
}